Workbook

Sheet Supplier Overview
A1: AOP POD Supplier Comparative Analysis — LunarAuraDesignStore
A2: Report Date: Feb 24, 2026 | Current Provider: Printify (MWW On Demand BP 450) | Target: Price-competitive AOP hoodies for multi-tier Etsy listings
A4: Supplier | B4: HQ / Mfg Location | C4: Founded | D4: AOP Specialization | E4: Product Range | F4: Etsy Integration | G4: API Available | H4: Shopify App Rating | I4: Key Strength | J4: Key Weakness | K4: Overall Score
A5: Printify (Current) | B5: USA / Multi-provider network | C5: 2015 | D5: Yes (via providers) | E5: 900+ products | F5: Native | G5: Yes (REST API) | H5: 4.7 / 5 | I5: Largest provider network, competitive routing | J5: Quality varies by provider | K5: =Scoring!I3 -> 7.8
A6: Subliminator | B6: Netherlands / China mfg | C6: 2018 | D6: AOP-first (cut & sew) | E6: 150+ AOP products | F6: Coming Soon | G6: Via Shopify only | H6: 4.5 / 5 | I6: Best-in-class AOP print quality | J6: Limited product range, no Etsy yet | K6: =Scoring!I4 -> 6.15
A7: Merchize | B7: USA / Vietnam mfg | C7: 2018 | D7: Strong AOP focus | E7: 1,000+ products | F7: Native | G7: Yes (REST API) | H7: 3.8 / 5 | I7: Lowest AOP base costs, Vietnam factory | J7: Mixed reviews, 7% processing fee | K7: =Scoring!I5 -> 7.55
A8: AOP+ | B8: London, UK / UK mfg | C8: 2009 | D8: AOP + DTG specialist | E8: 200+ products | F8: Native | G8: App-based only | H8: 4.2 / 5 | I8: Eco-friendly, great quality, UK production | J8: High US shipping, slower delivery | K8: =Scoring!I6 -> 7.05
A9: Gooten | B9: USA / Multi-provider | C9: 2013 | D9: Yes (via providers) | E9: 525+ products | F9: Via 3rd party | G9: Yes (REST API) | H9: 3.7 / 5 | I9: Free robust API, VIM volume discounts | J9: QC inconsistencies, no direct Etsy | K9: =Scoring!I7 -> 6.85
A10: Printful | B10: USA / Global facilities | C10: 2013 | D10: Yes (sublimation) | E10: 350+ products | F10: Native | G10: Yes (REST API) | H10: 4.4 / 5 | I10: Best QC (0.24% reshipment), branding | J10: Highest prices, AOP costs premium | K10: =Scoring!I8 -> 7.95
A11: HugePOD | B11: China | C11: 2020 | D11: AOP-focused | E11: 500+ styles | F11: No | G11: No | H11: 3.2 / 5 (Trustpilot) | I11: Very low prices, bulk discounts | J11: Quality inconsistent, slow shipping | K11: =Scoring!I9 -> 4.55
A12: Yoycol | B12: China (Shenzhen) | C12: 2016 | D12: AOP-first (800+ AOP) | E12: 800+ products | F12: Native | G12: Yes — Full REST API (V4) | H12: 4.4 / 5 | I12: Cheapest AOP on market, 3D mockup tools | J12: China shipping (7-20 days), no thread color match | K12: =Scoring!I11 -> 7.85
A13: SPOD (Spreadshirt) | B13: Germany / EU + US | C13: 2002 | D13: No AOP hoodies | E13: 250+ products | F13: Native | G13: Yes (REST API) | H13: 4.0 / 5 | I13: 48hr production, great DTG | J13: NO AOP hoodies available | K13: =Scoring!I10 -> 7.55

Sheet Pricing Comparison
A1: AOP Hoodie Pricing — Cost Per Unit Comparison (USD)
A2: All prices in USD. Shipping to continental US. Size M baseline unless noted. Blue = input assumptions you can change.
A4: ASSUMPTIONS (editable)
A5: Your Etsy Sale Price | B5: 74.99
A6: Etsy Transaction Fee | B6: 0.065
A7: Etsy Listing Fee | B7: 0.2
A8: Etsy Payment Processing | B8: 0.03
A9: Etsy Offsite Ads (est.) | B9: 0.15
A11: Supplier | B11: AOP Hoodie Base Cost | C11: Shipping (US Std) | D11: Total Landed Cost | E11: Etsy Fees (on $74.99) | F11: Net Profit per Unit | G11: Profit Margin | H11: Production Time | I11: Ship to Customer | J11: Total Fulfillment | K11: Material | L11: Fabric Weight
A12: Printify (MWW — BP450) | B12: 44.25 | C12: 6.49 | D12: =B12+C12 -> 50.74 | E12: =$B$5*($B$6+$B$8+$B$9)+$B$7 -> 18.57255 | F12: =$B$5-D12-E12 -> 5.67745 | G12: =IF($B$5>0,F12/$B$5,0) -> 0.075709428 | H12: 3-6 days | I12: 3-7 days | J12: 6-13 days | K12: 86% poly / 14% cotton | L12: 8.85 oz/yd²
A13: Printify (Subliminator — BP592) | B13: 32 | C13: 0 | D13: =B13+C13 -> 32 | E13: =$B$5*($B$6+$B$8+$B$9)+$B$7 -> 18.57255 | F13: =$B$5-D13-E13 -> 24.41745 | G13: =IF($B$5>0,F13/$B$5,0) -> 0.32560941 | H13: 3-7 days | I13: 6-9 days | J13: 9-16 days | K13: 75% poly / 20% cotton / 5% spandex | L13: 7.7 oz/yd²
A14: Subliminator (Direct) | B14: 32 | C14: 0 | D14: =B14+C14 -> 32 | E14: =$B$5*($B$6+$B$8+$B$9)+$B$7 -> 18.57255 | F14: =$B$5-D14-E14 -> 24.41745 | G14: =IF($B$5>0,F14/$B$5,0) -> 0.32560941 | H14: 3-7 days | I14: 6-9 days | J14: 9-16 days | K14: 75% poly / 20% cotton / 5% spandex | L14: 7.7 oz/yd²
A15: Merchize (Lightweight) | B15: 15.5 | C15: 7.99 | D15: =B15+C15 -> 23.49 | E15: =$B$5*($B$6+$B$8+$B$9)+$B$7 -> 18.57255 | F15: =$B$5-D15-E15 -> 32.92745 | G15: =IF($B$5>0,F15/$B$5,0) -> 0.43909121 | H15: 2-6 days | I15: 4-7 days | J15: 6-13 days | K15: 100% polyester | L15: 260 GSM
A16: Merchize (Standard) | B16: 19 | C16: 7.99 | D16: =B16+C16 -> 26.99 | E16: =$B$5*($B$6+$B$8+$B$9)+$B$7 -> 18.57255 | F16: =$B$5-D16-E16 -> 29.42745 | G16: =IF($B$5>0,F16/$B$5,0) -> 0.39241832 | H16: 2-6 days | I16: 4-7 days | J16: 6-13 days | K16: 100% polyester | L16: 260 GSM
A17: AOP+ (Classic Hoodie) | B17: 18.99 | C17: 9.39 | D17: =B17+C17 -> 28.38 | E17: =$B$5*($B$6+$B$8+$B$9)+$B$7 -> 18.57255 | F17: =$B$5-D17-E17 -> 28.03745 | G17: =IF($B$5>0,F17/$B$5,0) -> 0.37388252 | H17: 3-5 days | I17: 5-10 days | J17: 8-15 days | K17: 80% poly / 20% cotton | L17: 280 GSM
A18: Gooten (AOP Hoodie) | B18: 28 | C18: 7.5 | D18: =B18+C18 -> 35.5 | E18: =$B$5*($B$6+$B$8+$B$9)+$B$7 -> 18.57255 | F18: =$B$5-D18-E18 -> 20.91745 | G18: =IF($B$5>0,F18/$B$5,0) -> 0.27893652 | H18: 4-8 days | I18: 3-7 days | J18: 7-15 days | K18: 95% polyester / 5% spandex | L18: 8.0 oz/yd²
A19: Printful (AOP Recycled) | B19: 33.5 | C19: 4.2 | D19: =B19+C19 -> 37.7 | E19: =$B$5*($B$6+$B$8+$B$9)+$B$7 -> 18.57255 | F19: =$B$5-D19-E19 -> 18.71745 | G19: =IF($B$5>0,F19/$B$5,0) -> 0.24959928 | H19: 2-5 days | I19: 3-5 days | J19: 5-10 days | K19: 70% poly / 27% cotton / 3% elastane | L19: 8.85 oz/yd²
A20: HugePOD (AOP Hoodie) | B20: 16 | C20: 8 | D20: =B20+C20 -> 24 | E20: =$B$5*($B$6+$B$8+$B$9)+$B$7 -> 18.57255 | F20: =$B$5-D20-E20 -> 32.41745 | G20: =IF($B$5>0,F20/$B$5,0) -> 0.43229031 | H20: 5-10 days | I20: 10-20 days | J20: 15-30 days | K20: 100% polyester | L20: Thin (~200 GSM)
A21: Yoycol (AOP Hoodie) | B21: 6.2 | C21: 6.01 | D21: =B21+C21 -> 12.21 | E21: =$B$5*($B$6+$B$8+$B$9)+$B$7 -> 18.57255 | F21: =$B$5-D21-E21 -> 44.20745 | G21: =IF($B$5>0,F21/$B$5,0) -> 0.58951127 | H21: 2-5 days | I21: 7-20 days | J21: 9-25 days | K21: 100% polyester | L21: ~260 GSM (est.)

Sheet API & Integration
A1: API Capabilities & Platform Integration Comparison
A3: Supplier | B3: REST API | C3: API Docs | D3: Product Creation via API | E3: Order Mgmt via API | F3: Etsy Integration | G3: Shopify Integration | H3: Automation Friendliness
A4: Printify (Current) | B4: Yes — Full REST API | C4: developers.printify.com | D4: Yes — create products, upload images | E4: Yes — create/cancel/ship | F4: Native (auto-sync) | G4: Native (auto-sync) | H4: EXCELLENT
A5: Subliminator | B5: No public API | C5: N/A | D5: No — Shopify app only | E5: Auto via Shopify orders | F5: Coming Soon | G5: Native app | H5: LIMITED
A6: Merchize | B6: Yes — REST API | C6: Via dashboard | D6: Yes — product + variants | E6: Yes — order placement | F6: Native | G6: Private/custom app | H6: GOOD
A7: AOP+ | B7: No public API | C7: N/A | D7: No — app-based only | E7: Auto via platform orders | F7: Native app | G7: Native app | H7: LIMITED
A8: Gooten | B8: Yes — Full REST API | C8: developer.gooten.com | D8: Yes — full product CRUD | E8: Yes — create/track/cancel | F8: Via 3rd party | G8: Native app | H8: EXCELLENT
A9: Printful | B9: Yes — Full REST API | C9: developers.printful.com | D9: Yes — create products, mockups | E9: Yes — full order lifecycle | F9: Native (auto-sync) | G9: Native (auto-sync) | H9: EXCELLENT
A10: HugePOD | B10: No public API | C10: N/A | D10: No | E10: No — manual order entry | F10: No | G10: No | H10: NONE
A11: SPOD | B11: Yes — REST API | C11: api.spod.com/docs | D11: Yes — product creation | E11: Yes — order fulfillment | F11: Native | G11: Native app | H11: GOOD (no AOP)
A12: Yoycol | B12: Yes — Full REST API (V4) | C12: yoycol.com/api/2025/redoc | D12: Yes — product templates, store products, variant upserts | E12: Yes — create/update/cancel/track orders | F12: Native app | G12: Native app | H12: EXCELLENT

Sheet Quality & Reviews
A1: Product Quality & User Reviews Summary
A3: Supplier | B3: Print Method | C3: Print Quality (1-10) | D3: Fabric Quality (1-10) | E3: Consistency (1-10) | F3: User Sentiment | G3: Key Review Quotes
A4: Printify (MWW) | B4: Dye-sublimation (cut & sew) | C4: 8 | D4: 8 | E4: 7 | F4: Positive | G4: Solid AOP quality. Provider-dependent consistency.
A5: Subliminator | B5: Cut & sew sublimation | C5: 10 | D5: 9 | E5: 9 | F5: Very Positive | G5: "Best AOP quality on the market." Color-matched stitching. Superb fabrics.
A6: Merchize | B6: Cut & sew sublimation | C6: 7 | D6: 6 | E6: 6 | F6: Mixed | G6: Low costs but some wrong-product and double-charge reports. Vietnam factory.
A7: AOP+ | B7: DTG + sublimation | C7: 9 | D7: 8 | E7: 8 | F7: Positive | G7: "By far one of the best print quality in POD." Eco-focus. UK made.
A8: Gooten | B8: Dye-sublimation | C8: 7 | D8: 7 | E8: 5 | F8: Mixed | G8: Good at scale with VIM. 20% misprint rate reported by some users.
A9: Printful | B9: Dye-sublimation | C9: 9 | D9: 9 | E9: 9 | F9: Very Positive | G9: 0.24% reshipment rate. Premium blanks. Most consistent quality.
A10: HugePOD | B10: Sublimation | C10: 5 | D10: 4 | E10: 3 | F10: Negative | G10: Material mismatch (polyester vs advertised cotton). Month-long shipping.
A11: SPOD | B11: DTG / DTF only | C11: 8 | D11: 8 | E11: 9 | F11: Positive | G11: 48hr production. No AOP hoodies — DTG/DTF only.
A12: Yoycol | B12: Cut & sew sublimation | C12: 7 | D12: 7 | E12: 6 | F12: Positive | G12: "Best cost effective AOP company." Vibrant colors, soft. No thread color match.

Sheet Scoring
A1: Weighted Scoring Model — Best AOP Supplier for LunarAuraDesignStore
A2: Weights → | B2: Price Competitiveness | C2: Print Quality | D2: API / Automation | E2: Etsy Integration | F2: Fulfillment Speed | G2: Material Quality | H2: Scalability | I2: Weighted Total | J2: Rank
A3: Printify (MWW) | B3: 5 | C3: 8 | D3: 10 | E3: 10 | F3: 7 | G3: 8 | H3: 9 | I3: =B3*0.25+C3*0.2+D3*0.15+E3*0.15+F3*0.1+G3*0.1+H3*0.05 -> 7.8 | J3: =RANK(I3,I$3:I$11) -> 3
A4: Subliminator | B4: 7 | C4: 10 | D4: 3 | E4: 2 | F4: 5 | G4: 9 | H4: 5 | I4: =B4*0.25+C4*0.2+D4*0.15+E4*0.15+F4*0.1+G4*0.1+H4*0.05 -> 6.15 | J4: =RANK(I4,I$3:I$11) -> 8
A5: Merchize | B5: 9 | C5: 7 | D5: 7 | E5: 8 | F5: 7 | G5: 6 | H5: 7 | I5: =B5*0.25+C5*0.2+D5*0.15+E5*0.15+F5*0.1+G5*0.1+H5*0.05 -> 7.55 | J5: =RANK(I5,I$3:I$11) -> 4
A6: AOP+ | B6: 8 | C6: 9 | D6: 3 | E6: 8 | F6: 5 | G6: 8 | H6: 6 | I6: =B6*0.25+C6*0.2+D6*0.15+E6*0.15+F6*0.1+G6*0.1+H6*0.05 -> 7.05 | J6: =RANK(I6,I$3:I$11) -> 6
A7: Gooten | B7: 7 | C7: 7 | D7: 10 | E7: 4 | F7: 5 | G7: 7 | H7: 8 | I7: =B7*0.25+C7*0.2+D7*0.15+E7*0.15+F7*0.1+G7*0.1+H7*0.05 -> 6.85 | J7: =RANK(I7,I$3:I$11) -> 7
A8: Printful | B8: 4 | C8: 9 | D8: 10 | E8: 10 | F8: 8 | G8: 9 | H8: 9 | I8: =B8*0.25+C8*0.2+D8*0.15+E8*0.15+F8*0.1+G8*0.1+H8*0.05 -> 7.95 | J8: =RANK(I8,I$3:I$11) -> 1
A9: HugePOD | B9: 10 | C9: 5 | D9: 1 | E9: 1 | F9: 2 | G9: 4 | H9: 3 | I9: =B9*0.25+C9*0.2+D9*0.15+E9*0.15+F9*0.1+G9*0.1+H9*0.05 -> 4.55 | J9: =RANK(I9,I$3:I$11) -> 9
A10: SPOD | B10: 6 | C10: 8 | D10: 8 | E10: 8 | F10: 9 | G10: 8 | H10: 7 | I10: =B10*0.25+C10*0.2+D10*0.15+E10*0.15+F10*0.1+G10*0.1+H10*0.05 -> 7.55 | J10: =RANK(I10,I$3:I$11) -> 5
A11: Yoycol | B11: 10 | C11: 7 | D11: 9 | E11: 8 | F11: 3 | G11: 7 | H11: 8 | I11: =B11*0.25+C11*0.2+D11*0.15+E11*0.15+F11*0.1+G11*0.1+H11*0.05 -> 7.85 | J11: =RANK(I11,I$3:I$11) -> 2
A13: Weight: | B13: 0.25 | C13: 0.2 | D13: 0.15 | E13: 0.15 | F13: 0.1 | G13: 0.1 | H13: 0.05

Sheet Recommendation
A1: Strategic Recommendation for LunarAuraDesignStore
A3: TIER | B3: RECOMMENDED SUPPLIER | C3: PRODUCT | D3: EST. COST (LANDED) | E3: SALE PRICE
A4: Premium (Hero) | B4: Printify — MWW On Demand (BP 450) | C4: AOP Hoodie (86/14 blend) | D4: ='Pricing Comparison'!D12 -> 50.74 | E4: $74.99
A5: Mid-Tier | B5: Merchize OR AOP+ | C5: AOP Hoodie (lightweight) | D5: ='Pricing Comparison'!D15 -> 23.49 | E5: $49.99
A6: Entry | B6: Merchize | C6: AOP Tee (lightweight) | E6: $29.99
A8: KEY FINDINGS
A9: 1. | B9: KEEP Printify/MWW for premium hoodies — best fabric blend, fastest US fulfillment, native Etsy + full API
A10: 2. | B10: ADD Merchize as secondary provider — 60% lower base cost ($15.50 vs $44.25), REST API available, native Etsy
A11: 3. | B11: CONSIDER AOP+ for UK/EU orders — great quality, eco-friendly, but high US shipping ($9.39)
A12: 4. | B12: SKIP Subliminator for now — best quality but NO Etsy integration and NO public API (Shopify-only)
A13: 5. | B13: SKIP HugePOD — cheapest but quality too inconsistent, no integrations, 15-30 day fulfillment
A14: 7. | B14: STRONG CONTENDER: Yoycol — $6.20 base AOP hoodie + full REST API (V4) with product creation, variant mgmt, order lifecycle, shipping quotes. Native Etsy app. Caveat: China shipping (7-20 days), no thread color matching. 59% margin at $74.99.
A16: DUAL-SUPPLIER STRATEGY
A17: Premium customers get MWW quality (86/14 cotton-blend, 8.85oz). Price-sensitive customers get Merchize value (100% poly, lighter). Both work via API + Etsy.
